nonebot_plugin_fishing2/__init__.py
nonebot_plugin_fishing2/config.py
nonebot_plugin_fishing2/data_source.py
nonebot_plugin_fishing2/fish_helper.py
nonebot_plugin_fishing2/migrations/68463f3e5f33_.py
nonebot_plugin_fishing2/migrations/7609e6d106dd_init_db.py
nonebot_plugin_fishing2/migrations/c5ab992c9af3_add_achievements.py
nonebot_plugin_fishing2/migrations/e9015df43907_add_special_fishes_field.py
nonebot_plugin_fishing2/migrations/f70bdeaec7a4_add_specialfishes_table.py
nonebot_plugin_fishing2/model.py
nonebot_plugin_fishing2-1.0.1.dist-info/METADATA
nonebot_plugin_fishing2-1.0.1.dist-info/WHEEL
nonebot_plugin_fishing2-1.0.1.dist-info/licenses/LICENSE
nonebot_plugin_fishing2-1.0.1.dist-info/RECORD
