Metadata-Version: 2.4
Name: nonebot-plugin-fishing2
Version: 1.0.1
Summary: 更好的电子钓鱼
License-Expression: MIT
License-File: LICENSE
Keywords: fishing
Author: Polaris_Light
Author-email: 995905922@qq.com
Requires-Python: >=3.8
Classifier: Programming Language :: Python :: 3
Classifier: Programming Language :: Python :: 3.8
Classifier: Programming Language :: Python :: 3.9
Classifier: Programming Language :: Python :: 3.10
Classifier: Programming Language :: Python :: 3.11
Classifier: Programming Language :: Python :: 3.12
Classifier: Programming Language :: Python :: 3.13
Classifier: Programming Language :: Python :: 3.14
Requires-Dist: nonebot-adapter-onebot (>=2.0.0-beta.1)
Requires-Dist: nonebot-plugin-localstore (>=0.6.0)
Requires-Dist: nonebot-plugin-orm (>=0.7.1)
Requires-Dist: nonebot2 (>=2.2.1)
Requires-Dist: pydantic (>=1.10)
Requires-Dist: sqlalchemy (>=2.0.27)
Project-URL: Homepage, https://github.com/GLDYM/nonebot-plugin-fishing2
